animalsay/__init__.py
animalsay/__main__.py
animalsay/animalsay.py
animalsay_jubilee-0.1.4.dist-info/licenses/LICENSE
animalsay_jubilee-0.1.4.dist-info/METADATA
animalsay_jubilee-0.1.4.dist-info/WHEEL
animalsay_jubilee-0.1.4.dist-info/entry_points.txt
animalsay_jubilee-0.1.4.dist-info/top_level.txt
animalsay_jubilee-0.1.4.dist-info/RECORD
