Metadata-Version: 2.4
Name: animalsay-jubilee
Version: 0.1.4
Summary: A fun package that makes animals say things with moods in ASCII art!
Author-email: Jasmine Zhu <jz5457@nyu.edu>
License:                     GNU GENERAL PUBLIC LICENSE
Project-URL: Homepage, https://github.com/swe-students-fall2025/3-python-package-team_jubilee
Project-URL: Repository, https://github.com/swe-students-fall2025/3-python-package-team_jubilee.git
Project-URL: Bug Tracker, https://github.com/swe-students-fall2025/3-python-package-team_jubilee/issues
Keywords: python,package,ascii,animals,fun,terminal
Classifier: Development Status :: 4 - Beta
Classifier: Intended Audience :: Developers
Classifier: License :: OSI Approved :: MIT License
Classifier: Programming Language :: Python :: 3
Classifier: Programming Language :: Python :: 3.8
Classifier: Programming Language :: Python :: 3.9
Classifier: Programming Language :: Python :: 3.10
Classifier: Programming Language :: Python :: 3.11
Classifier: Programming Language :: Python :: 3.12
Classifier: Operating System :: OS Independent
Classifier: Topic :: Utilities
Classifier: Topic :: Software Development :: Libraries :: Python Modules
Requires-Python: >=3.8
License-File: LICENSE
Provides-Extra: dev
Requires-Dist: pytest; extra == "dev"
Requires-Dist: build; extra == "dev"
Requires-Dist: twine; extra == "dev"
Requires-Dist: coverage; extra == "dev"
Requires-Dist: pytest-cov; extra == "dev"
Dynamic: license-file
